LICENSE.md
MANIFEST.in
README.md
requirements.txt
setup.cfg
setup.py
btoolkit/__init__.py
btoolkit/auth.py
btoolkit/constant.py
btoolkit/crypto.py
btoolkit/error.py
btoolkit/xfile.py
btoolkit/xfunc.py
btoolkit/xglobal.py
btoolkit/xtype.py
btoolkit.egg-info/PKG-INFO
btoolkit.egg-info/SOURCES.txt
btoolkit.egg-info/dependency_links.txt
btoolkit.egg-info/not-zip-safe
btoolkit.egg-info/requires.txt
btoolkit.egg-info/top_level.txt
btoolkit/__pycache__/config.cpython-39.pyc
btoolkit/__pycache__/nacos_client.cpython-39.pyc
btoolkit/__pycache__/web.cpython-39.pyc
btoolkit/asynch/__init__.py
btoolkit/asynch/async_call.py
btoolkit/asynch/message_queue.py
btoolkit/asynch/mq_backend_rdb.py
btoolkit/cli/__init__.py
btoolkit/cli/app.py
btoolkit/cli/localize.py
btoolkit/cli/rdb_migrate.py
btoolkit/cli/test.py
btoolkit/cli/templates/rdb_migrate/README
btoolkit/cli/templates/rdb_migrate/alembic.ini.mako
btoolkit/cli/templates/rdb_migrate/env.py
btoolkit/cli/templates/rdb_migrate/script.py.mako
btoolkit/config/__init__.py
btoolkit/config/nacos_client.py
btoolkit/database/__init__.py
btoolkit/database/illegalwords.txt
btoolkit/database/rdb_alchemy.py
btoolkit/database/rdb_table.py
btoolkit/database/validator.py
btoolkit/web/__init__.py
btoolkit/web/flaskapp_manager.py
btoolkit/web/html_parser.py
btoolkit/web/jinja_extension.py
btoolkit/web/web_base.py
btoolkit/web/web_constant.py
btoolkit/web/wsgiapp_manager.py