Metadata-Version: 2.1
Name: btoolkit
Version: 0.5.1b0
Summary: Basic tools for web application.
Home-page: UNKNOWN
Author: Dabai
Author-email: zhgbai@163.com
License: MIT
Keywords: Web,Flask,ETL
Platform: any
Classifier: Framework :: Flask
Classifier: Development Status :: 4 - Beta
Classifier: Environment :: Web Environment
Classifier: Intended Audience :: Developers
Classifier: License :: OSI Approved :: MIT License
Classifier: Operating System :: OS Independent
Classifier: Programming Language :: Python :: 3.6
Classifier: Programming Language :: Python :: 3.7
Classifier: Programming Language :: Python :: 3.8
Classifier: Topic :: Software Development :: Libraries :: Python Modules
License-File: LICENSE.md
